Workbook

Sheet Assumptions
A1: WORKFORCE COST SCENARIO MODEL — ASSUMPTIONS
A3: Input | B3: Value | C3: Notes
A4: Horizon (months) | B4: 24 | C4: Projection window
A5: Retention raise % | B5: 0.08 | C5: Targeted raise to watchlist
A6: Risk reduction from raise | B6: 0.45 | C6: Fractional cut to churn prob after raise
A7: Productivity gap (months) | B7: 3 | C7: Lost productivity per backfill (reactive)
A9: Replacement cost multiplier by job level (x annual salary):
A10: L1 - Junior | B10: 0.5
A11: L2 - Mid | B11: 0.75
A12: L3 - Senior | B12: 1
A13: L4 - Lead | B13: 1.25
A14: L5 - Manager | B14: 1.5
A15: L6 - Director | B15: 2

Sheet Employee Detail
A1: Employee ID | B1: Department | C1: Job Level | D1: Base Salary (EUR) | E1: Risk Score | F1: Annual Churn Prob | G1: On Watchlist | H1: Repl. Multiplier | I1: Replacement Cost (EUR) | J1: P(leave 24m) | K1: Exp. Replacement (Status Quo) | L1: Exp. Replacement (Proactive)
A2: DF-100053 | B2: Customer Success | C2: L3 - Senior | D2: 57643 | E2: 78.7 | F2: =E2/100 | G2: Yes | H2: =VLOOKUP(C2,Assumptions!$A$10:$B$15,2,FALSE) | I2: =D2*H2 | J2: =1-(1-F2)^(Assumptions!$B$4/12) | K2: =J2*I2 | L2: =IF(G2="Yes",(1-(1-F2*(1-Assumptions!$B$6))^(Assumptions!$B$4/12))*I2,K2)
A3: DF-100502 | B3: Engineering | C3: L2 - Mid | D3: 67306 | E3: 77.4 | F3: =E3/100 | G3: Yes | H3: =VLOOKUP(C3,Assumptions!$A$10:$B$15,2,FALSE) | I3: =D3*H3 | J3: =1-(1-F3)^(Assumptions!$B$4/12) | K3: =J3*I3 | L3: =IF(G3="Yes",(1-(1-F3*(1-Assumptions!$B$6))^(Assumptions!$B$4/12))*I3,K3)
A4: DF-100566 | B4: Customer Success | C4: L3 - Senior | D4: 69711 | E4: 77.1 | F4: =E4/100 | G4: Yes | H4: =VLOOKUP(C4,Assumptions!$A$10:$B$15,2,FALSE) | I4: =D4*H4 | J4: =1-(1-F4)^(Assumptions!$B$4/12) | K4: =J4*I4 | L4: =IF(G4="Yes",(1-(1-F4*(1-Assumptions!$B$6))^(Assumptions!$B$4/12))*I4,K4)
A5: DF-100069 | B5: Customer Success | C5: L3 - Senior | D5: 63602 | E5: 76.5 | F5: =E5/100 | G5: Yes | H5: =VLOOKUP(C5,Assumptions!$A$10:$B$15,2,FALSE) | I5: =D5*H5 | J5: =1-(1-F5)^(Assumptions!$B$4/12) | K5: =J5*I5 | L5: =IF(G5="Yes",(1-(1-F5*(1-Assumptions!$B$6))^(Assumptions!$B$4/12))*I5,K5)
A6: DF-100663 | B6: Engineering | C6: L1 - Junior | D6: 52094 | E6: 75.9 | F6: =E6/100 | G6: Yes | H6: =VLOOKUP(C6,Assumptions!$A$10:$B$15,2,FALSE) | I6: =D6*H6 | J6: =1-(1-F6)^(Assumptions!$B$4/12) | K6: =J6*I6 | L6: =IF(G6="Yes",(1-(1-F6*(1-Assumptions!$B$6))^(Assumptions!$B$4/12))*I6,K6)
A7: DF-100152 | B7: Operations | C7: L4 - Lead | D7: 84006 | E7: 75.8 | F7: =E7/100 | G7: Yes | H7: =VLOOKUP(C7,Assumptions!$A$10:$B$15,2,FALSE) | I7: =D7*H7 | J7: =1-(1-F7)^(Assumptions!$B$4/12) | K7: =J7*I7 | L7: =IF(G7="Yes",(1-(1-F7*(1-Assumptions!$B$6))^(Assumptions!$B$4/12))*I7,K7)
A8: DF-100232 | B8: Finance | C8: L2 - Mid | D8: 61765 | E8: 75 | F8: =E8/100 | G8: Yes | H8: =VLOOKUP(C8,Assumptions!$A$10:$B$15,2,FALSE) | I8: =D8*H8 | J8: =1-(1-F8)^(Assumptions!$B$4/12) | K8: =J8*I8 | L8: =IF(G8="Yes",(1-(1-F8*(1-Assumptions!$B$6))^(Assumptions!$B$4/12))*I8,K8)
A9: DF-100642 | B9: Sales | C9: L1 - Junior | D9: 44002 | E9: 74.9 | F9: =E9/100 | G9: Yes | H9: =VLOOKUP(C9,Assumptions!$A$10:$B$15,2,FALSE) | I9: =D9*H9 | J9: =1-(1-F9)^(Assumptions!$B$4/12) | K9: =J9*I9 | L9: =IF(G9="Yes",(1-(1-F9*(1-Assumptions!$B$6))^(Assumptions!$B$4/12))*I9,K9)
A10: DF-100509 | B10: People/HR | C10: L1 - Junior | D10: 45771 | E10: 73.6 | F10: =E10/100 | G10: Yes | H10: =VLOOKUP(C10,Assumptions!$A$10:$B$15,2,FALSE) | I10: =D10*H10 | J10: =1-(1-F10)^(Assumptions!$B$4/12) | K10: =J10*I10 | L10: =IF(G10="Yes",(1-(1-F10*(1-Assumptions!$B$6))^(Assumptions!$B$4/12))*I10,K10)
A11: DF-100158 | B11: Customer Success | C11: L1 - Junior | D11: 50498 | E11: 73.6 | F11: =E11/100 | G11: Yes | H11: =VLOOKUP(C11,Assumptions!$A$10:$B$15,2,FALSE) | I11: =D11*H11 | J11: =1-(1-F11)^(Assumptions!$B$4/12) | K11: =J11*I11 | L11: =IF(G11="Yes",(1-(1-F11*(1-Assumptions!$B$6))^(Assumptions!$B$4/12))*I11,K11)
A12: DF-100358 | B12: Data & Analytics | C12: L1 - Junior | D12: 41026 | E12: 72.3 | F12: =E12/100 | G12: Yes | H12: =VLOOKUP(C12,Assumptions!$A$10:$B$15,2,FALSE) | I12: =D12*H12 | J12: =1-(1-F12)^(Assumptions!$B$4/12) | K12: =J12*I12 | L12: =IF(G12="Yes",(1-(1-F12*(1-Assumptions!$B$6))^(Assumptions!$B$4/12))*I12,K12)
A13: DF-100132 | B13: Engineering | C13: L6 - Director | D13: 69256 | E13: 71.8 | F13: =E13/100 | G13: Yes | H13: =VLOOKUP(C13,Assumptions!$A$10:$B$15,2,FALSE) | I13: =D13*H13 | J13: =1-(1-F13)^(Assumptions!$B$4/12) | K13: =J13*I13 | L13: =IF(G13="Yes",(1-(1-F13*(1-Assumptions!$B$6))^(Assumptions!$B$4/12))*I13,K13)
... A525: DF-100144 | B525: Engineering | C525: L2 - Mid | D525: 82660 | E525: 5.2 | F525: =E525/100 | G525: No | H525: =VLOOKUP(C525,Assumptions!$A$10:$B$15,2,FALSE) | I525: =D525*H525 | J525: =1-(1-F525)^(Assumptions!$B$4/12) | K525: =J525*I525 | L525: =IF(G525="Yes",(1-(1-F525*(1-Assumptions!$B$6))^(Assumptions!$B$4/12))*I525,K525)

Sheet Scenario Summary
A1: 24-MONTH WORKFORCE COST — SCENARIO COMPARISON (EUR)
A3: Component | B3: A. Status Quo | C3: B. Proactive Retention | D3: C. Reactive (Do Nothing)
A4: Base salary cost | B4: =SUM('Employee Detail'!D2:D525)*Assumptions!$B$4/12 | C4: =B4+SUMIF('Employee Detail'!G2:G525,"Yes",'Employee Detail'!D2:D525)*Assumptions!$B$5*Assumptions!$B$4/12 | D4: =B4
A5: Retention investment (raises) | B5: 0 | C5: =C4-B4 | D5: 0
A6: Expected replacement cost | B6: =SUM('Employee Detail'!K2:K525) | C6: =SUM('Employee Detail'!L2:L525) | D6: =B6
A7: Productivity gap cost | B7: 0 | C7: 0 | D7: =SUMPRODUCT('Employee Detail'!J2:J525,'Employee Detail'!D2:D525)*Assumptions!$B$7/12
A8: TOTAL 24-MONTH COST | B8: =B4+B6+B7 | C8: =C4+C6+C7 | D8: =D4+D6+D7
A10: Cost vs Status Quo | B10: =B8-$B$8 | C10: =C8-$B$8 | D10: =D8-$B$8
A12: Net saving: Proactive vs Reactive | B12: =D8-C8
A14: Read: Proactive retention spends on targeted raises but avoids most replacement cost; Reactive eats full replacement plus a productivity gap.
